adk_agui_middleware/__init__.py
adk_agui_middleware/endpoint.py
adk_agui_middleware/py.typed
adk_agui_middleware/base_abc/__init__.py
adk_agui_middleware/base_abc/handler.py
adk_agui_middleware/base_abc/sse_service.py
adk_agui_middleware/config/__init__.py
adk_agui_middleware/config/log.py
adk_agui_middleware/data_model/__init__.py
adk_agui_middleware/data_model/common.py
adk_agui_middleware/data_model/config.py
adk_agui_middleware/data_model/context.py
adk_agui_middleware/data_model/error.py
adk_agui_middleware/data_model/event.py
adk_agui_middleware/data_model/log.py
adk_agui_middleware/data_model/queue.py
adk_agui_middleware/data_model/session.py
adk_agui_middleware/event/__init__.py
adk_agui_middleware/event/agui_event.py
adk_agui_middleware/event/agui_type.py
adk_agui_middleware/event/error_event.py
adk_agui_middleware/event/event_translator.py
adk_agui_middleware/handler/__init__.py
adk_agui_middleware/handler/agui_user.py
adk_agui_middleware/handler/history.py
adk_agui_middleware/handler/queue.py
adk_agui_middleware/handler/running.py
adk_agui_middleware/handler/session.py
adk_agui_middleware/handler/session_lock_handler.py
adk_agui_middleware/handler/user_message.py
adk_agui_middleware/loggers/__init__.py
adk_agui_middleware/loggers/exception.py
adk_agui_middleware/loggers/logger.py
adk_agui_middleware/loggers/record_log.py
adk_agui_middleware/loggers/record_request_log.py
adk_agui_middleware/manager/__init__.py
adk_agui_middleware/manager/queue.py
adk_agui_middleware/manager/session.py
adk_agui_middleware/pattern/__init__.py
adk_agui_middleware/pattern/singleton.py
adk_agui_middleware/service/__init__.py
adk_agui_middleware/service/history_service.py
adk_agui_middleware/service/sse_service.py
adk_agui_middleware/service/state_service.py
adk_agui_middleware/tools/__init__.py
adk_agui_middleware/tools/async_queue_iterator.py
adk_agui_middleware/tools/default_session_id.py
adk_agui_middleware/tools/frontend_tool.py
adk_agui_middleware/tools/function_name.py
adk_agui_middleware-1.4.2.dist-info/METADATA
adk_agui_middleware-1.4.2.dist-info/WHEEL
adk_agui_middleware-1.4.2.dist-info/licenses/LICENSE
adk_agui_middleware-1.4.2.dist-info/RECORD
