Metadata-Version: 2.4
Name: adk-agui-middleware
Version: 1.4.2
Summary: Python middleware bridging Google ADK agents with AGUI protocol via Server-Sent Events for real-time agent interactions
Project-URL: Homepage, https://github.com/trendmicro/adk-agui-middleware
Project-URL: Repository, https://github.com/trendmicro/adk-agui-middleware.git
Project-URL: Documentation, https://github.com/trendmicro/adk-agui-middleware#readme
Project-URL: Bug Tracker, https://github.com/trendmicro/adk-agui-middleware/issues
Author-email: denny_lee <denny_lee@trendmicro.com>
Maintainer-email: denny_lee <denny_lee@trendmicro.com>
License: MIT License
License-File: LICENSE
Keywords: agent,agui,fastapi,google-adk,middleware,sse
Classifier: Development Status :: 3 - Alpha
Classifier: Intended Audience :: Developers
Classifier: License :: OSI Approved :: MIT License
Classifier: Operating System :: OS Independent
Classifier: Programming Language :: Python :: 3
Classifier: Programming Language :: Python :: 3.10
Classifier: Programming Language :: Python :: 3.11
Classifier: Programming Language :: Python :: 3.12
Classifier: Programming Language :: Python :: 3.13
Classifier: Topic :: Internet :: WWW/HTTP :: HTTP Servers
Classifier: Topic :: Scientific/Engineering :: Artificial Intelligence
Classifier: Topic :: Software Development :: Libraries :: Python Modules
Requires-Python: >=3.10
Requires-Dist: ag-ui-protocol>=0.1.7
Requires-Dist: fastapi>=0.104.0
Requires-Dist: google-adk>=1.9.0
Requires-Dist: jsonpatch>=1.33
Requires-Dist: pydantic-settings>=2.10.1
Requires-Dist: pydantic>=2.11.7
Requires-Dist: sse-starlette>=1.6.5
